tdrpa/bot.exe
tdrpa/tdcore.cp38-win_amd64.pyd
tdcore-1.1.7.dist-info/METADATA
tdcore-1.1.7.dist-info/WHEEL
tdcore-1.1.7.dist-info/top_level.txt
tdcore-1.1.7.dist-info/RECORD
