Metadata-Version: 2.1
Name: tdcore
Version: 1.1.7
Summary: RPA SDK for software developers
Home-page: https://tdrpa.thingswell.cn
Author: tdrpa
Author-email: armstrong.wang@gmail.com
License: Apache 2.0
Keywords: RPA,tdRPA,uiautomation,uia
Platform: Windows Only
Classifier: Programming Language :: Python :: 3
Classifier: Operating System :: Microsoft :: Windows
Requires-Dist: keyboard
Requires-Dist: psutil
Requires-Dist: pywin32
Requires-Dist: Requests
Requires-Dist: tzlocal
Requires-Dist: uiautomation
